{"shenpizhuangtai":[{"value":"正常","key":1},{"value":"首营审批中","key":2},{"value":"首营修改中","key":3},{"value":"过期/不合格","key":4},{"value":"将过期","key":5}],"huoweizhuangtai":[{"value":"可使用","key":36},{"value":"使用中","key":37}],"xingbie":[{"value":"女","key":0},{"value":"男","key":1}],"mudikubie":[{"value":"常温库","key":1},{"value":"冷藏库","key":2}],"huowei":[{"value":"固定货位","key":5},{"value":"其他","key":6}],"xiaohuifangshi":[{"value":"空","key":0},{"value":"焚烧","key":1},{"value":"物化","key":2},{"value":"生化","key":3},{"value":"拆解","key":4},{"value":"填满","key":5}],"cunchuwenti":[{"value":"正常存储易变质","key":1},{"value":"存储条件特殊要求","key":2}],"buhuoleixing":[{"value":"主动补货","key":30},{"value":"被动补货","key":40}],"yuetaibianhao":[{"value":"01","key":1},{"value":"02","key":2},{"value":"03","key":3},{"value":"04","key":4}],"shangjia":[{"value":"有","key":1},{"value":"无","key":0}],"yanghujielun":[{"value":"继续销售","key":1},{"value":"停止销售","key":2}],"renwuzhuangtai":[{"value":"未索取","key":32},{"value":"拣货未完成","key":34},{"value":"拣货完成","key":36},{"value":"内复核完成","key":43},{"value":"准备外复核","key":45},{"value":"隐藏拣货任务","key":30},{"value":"下架任务已索取","key":27},{"value":"下架成功","key":28},{"value":"上架任务已索取","key":29},{"value":"上架成功","key":26}],"xiaohuimxzhuangtai":[{"value":"未销毁","key":0},{"value":"已销毁","key":1}],"yanghuleixing":[{"value":"普通养护","key":0},{"value":"重点养护","key":1}],"enable":[{"value":"启用","key":1},{"value":"禁用","key":2}],"chaifenlidu":[{"value":"小包装","key":1},{"value":"中包装","key":2},{"value":"大包装","key":3},{"value":"小数","key":4}],"yushoukuan":[{"value":"预收款","key":1}],"baozhuangdanwei":[{"value":"盒","key":1},{"value":"包","key":2},{"value":"袋","key":3},{"value":"副","key":4},{"value":"卷","key":5},{"value":"枚","key":6},{"value":"瓶","key":7},{"value":"台","key":8},{"value":"套","key":9},{"value":"条","key":10},{"value":"桶","key":11},{"value":"筒","key":12},{"value":"支","key":13},{"value":"贴","key":14},{"value":"罐","key":15},{"value":"克","key":16},{"value":"其他","key":17}],"songhuofangshi":[{"value":"公司配送","key":1},{"value":"客户自提","key":2},{"value":"委托配送","key":3}],"fujianjielun":[{"value":"合格","key":1},{"value":"不合格","key":2},{"value":"待验","key":3},{"value":"合格","key":1},{"value":"不合格","key":2},{"value":"待验","key":3}],"zhixiangguigesize":[{"value":"大规格","key":1},{"value":"中规格","key":2},{"value":"小规格","key":3}],"yxqzfs":[{"value":"长期","key":1},{"value":"手填","key":0}],"rukudingdanleixing":[{"value":"采购入库","key":0},{"value":"空进空出","key":1},{"value":"越库","key":2},{"value":"调账","key":3}],"shangpinjixing":[{"value":"片剂","key":1},{"value":"丸剂","key":2},{"value":"颗粒剂","key":3},{"value":"胶囊剂","key":4},{"value":"口服液体剂","key":5},{"value":"外用剂","key":6},{"value":"保健品及非药品","key":7},{"value":"器械","key":8},{"value":"针剂","key":9},{"value":"进口合资","key":10},{"value":"其他","key":25}],"jihuoweiyewuleixing":[{"value":"销售出库","key":4},{"value":"购进退出","key":1},{"value":"自提","key":2}],"tuikuanqudao":[{"value":"用户发起","key":1},{"value":"客服介入","key":2}],"buliangpinleixing":[{"value":"不合格","key":0},{"value":"近效期","key":1}],"cangkubianhao":[{"value":"001","key":1},{"value":"002","key":2}],"xukeleixing":[{"value":"商品类别","key":1},{"value":"剂型","key":2}],"yanshouzhuangtai":[{"value":"未验收","key":0},{"value":"部分验收","key":1},{"value":"验收完成","key":2}],"xiaohuizhuangtai":[{"value":"未销毁","key":0},{"value":"部分销毁","key":1},{"value":"全部销毁","key":2}],"jushouyewulaiyuan":[{"value":"入库收货","key":10},{"value":"入库验收","key":20},{"value":"销退收货","key":30},{"value":"销退验收","key":40}],"shifouqiyong":[{"value":"是","key":1},{"value":"否","key":2}],"wmsyxtyjhw":[{"value":"订单","key":1},{"value":"客户","key":2},{"value":"路线","key":3},{"value":"无","key":4}],"hwxdlx":[{"value":"整件","key":1},{"value":"散件","key":2},{"value":"整散混合","key":3},{"value":"整散分开","key":4}],"caigouleixing":[{"value":"采购入库单","key":1},{"value":"采购退出出库单","key":2},{"value":"采购退补价执行单","key":3}],"jihuoweileixing":[{"value":"中客户","key":1},{"value":"大客户","key":2},{"value":"普通客户","key":3},{"value":"小客户","key":4}],"buhuozhuangtai":[{"value":"完成","key":26},{"value":"补货下架","key":28}],"status":[{"value":"草稿状态","key":0},{"value":"编辑","key":10},{"value":"提交","key":20},{"value":"审核中","key":30},{"value":"审核通过","key":40},{"value":"否单","key":50},{"value":"归档","key":60}],"danjulaiyuan":[{"value":"app端","key":1},{"value":"第三方","key":2}],"wtrlx":[{"value":"提货委托人","key":1},{"value":"采购委托人","key":2}],"ABC":[{"value":"A","key":0},{"value":"B","key":1},{"value":"C","key":2}],"shifouqiyong3":[{"value":"否","key":3}],"ru":[{"value":"-","key":0}],"cheliangzhuangtai":[{"value":"报废","key":0},{"value":"正常","key":1}],"chufangfenlei":[{"value":"处方药","key":1},{"value":"甲类OTC","key":2},{"value":"乙类OTC","key":3},{"value":"其他","key":4}],"shifouqiyong2":[{"value":"空","key":1},{"value":"是","key":2}],"zhiliangfenlei":[{"value":"计生药品","key":1},{"value":"普通药品","key":2},{"value":"医疗器械","key":3},{"value":"其他","key":4}],"shifouqiyong1":[{"value":"空","key":1}],"sunyizhuangtai":[{"value":"未损益","key":0},{"value":"部分损益","key":1},{"value":"损益完成","key":2}],"xiaoshouxingzhi":[{"value":"经销","key":1},{"value":"代销","key":2},{"value":"联营","key":3}],"kubie":[{"value":"零货库A","key":1},{"value":"整货库B","key":2}],"jxqzt":[{"value":"正常","key":1},{"value":"已过期","key":2},{"value":"预警期","key":3}],"buhuo":[{"value":"有","key":1},{"value":"无","key":0}],"yunshugongju":[{"value":"冷藏车","key":1},{"value":"保温箱","key":2},{"value":"冷藏箱","key":3},{"value":"厢式货车","key":4},{"value":"其他封闭式车辆","key":5}],"sh":[{"value":"-","key":0}],"rongqileixing":[{"value":"拣选篮","key":2},{"value":"周转箱","key":3},{"value":"托盘","key":4},{"value":"推车","key":5},{"value":"笼车","key":6},{"value":"线棒小车","key":7},{"value":"冷藏箱","key":8},{"value":"虚拟容器","key":9}],"cunchutiaojian":[{"value":"常温","key":3},{"value":"阴凉","key":1},{"value":"冷藏","key":2}],"sj":[{"value":"有","key":1},{"value":"无","key":2}],"fjhdlx":[{"value":"销售出库","key":2},{"value":"采购退出","key":3},{"value":"自提","key":4},{"value":"异常剔除口","key":5}],"caozuo":[{"value":"冻结","key":1},{"value":"停止销售","key":2},{"value":"停止采购","key":3}],"shangpincaigou":[{"value":"恢复采购","key":1},{"value":"停止采购","key":0}],"bbzqfs":[{"value":"出厂日期","key":1},{"value":"失效日期","key":2}],"fapiaozhuangtai":[{"value":"未开票","key":0},{"value":"已开票","key":1}],"zhifufangshi":[{"value":"支付宝","key":1},{"value":"微信","key":2},{"value":"支票","key":3},{"value":"银行卡","key":4},{"value":"其他","key":0}],"zhaiyao":[{"value":"采购入库","key":1},{"value":"采购退出","key":2},{"value":"销售出库","key":3},{"value":"销售退回","key":4},{"value":"移库","key":5},{"value":"损溢","key":6},{"value":"补货","key":7}],"zdyhpz":[{"value":"已提交","key":20},{"value":"录入","key":1}],"wenkongfangshi":[{"value":"电脑控温","key":1},{"value":"机械控温","key":2}],"qiyeleixing":[{"value":"药品生产企业","key":1},{"value":"药品批发企业","key":2},{"value":"医疗器械生产企业","key":3},{"value":"医疗器械商业企业","key":4},{"value":"食品生产企业","key":5},{"value":"食品经营企业","key":6},{"value":"其他企业","key":7}],"phxqfs":[{"value":"批号无效期无","key":4},{"value":"批号无效期有","key":3},{"value":"批号有效期无","key":2},{"value":"批号有效期有","key":1}],"rongqileixing2":[{"value":"空","key":1}],"kehuleixing":[{"value":"医院","key":1},{"value":"终端","key":2},{"value":"诊所","key":3},{"value":"批发","key":4}],"rongqileixing1":[{"value":"托盘","key":1},{"value":"周转箱","key":2},{"value":"小车","key":3},{"value":"冷藏","key":4}],"kongjianxianzhitiaojian":[{"value":"数量限定","key":0},{"value":"体积限定","key":1},{"value":"长宽高限定","key":2},{"value":"重量限定","key":3},{"value":"托盘数限定","key":4},{"value":"箱数限定","key":5}],"shangpintaotai":[{"value":"淘汰","key":0},{"value":"不淘汰","key":1}],"xxx":[{"value":"零货","key":0},{"value":"整件","key":1}],"dingdanzhuangtai":[{"value":"待配送","key":1},{"value":"配送中","key":2},{"value":"已配送","key":3},{"value":"取消","key":4},{"value":"删除","key":5},{"value":"已拆单","key":6},{"value":"出库中","key":7},{"value":"退款审核中","key":90},{"value":"已退款","key":91},{"value":"未支付","key":10},{"value":"订单创建","key":0}],"waifuhezhuangtai":[{"value":"外复核未完成","key":45},{"value":"外复核完成","key":47}],"tuihuidingdanleixing":[{"value":"销售退回","key":0},{"value":"空进空出","key":1},{"value":"越库","key":2},{"value":"调账","key":3}],"shangpindalei":[{"value":"保健","key":1},{"value":"保健用品","key":2},{"value":"非药","key":3},{"value":"内服","key":4},{"value":"外用","key":5},{"value":"医疗器械","key":6},{"value":"其他","key":7}],"bocijihuaweihu":[{"value":"小客户混分集货位","key":1},{"value":"按客户类别匹配","key":2},{"value":"按业务类型匹配","key":3},{"value":"按提货方式匹配","key":4},{"value":"按承运商匹配","key":5},{"value":"按配送线路匹配","key":6}],"yuetaileixing":[{"value":"收货","key":1},{"value":"发货","key":2}],"kucunzhuangtai":[{"value":"合格","key":1},{"value":"不合格","key":2},{"value":"待验","key":3},{"value":"停售","key":4}],"ysgjzt":[{"value":"无法使用","key":0},{"value":"正常","key":1}],"shangpinxiaoshou":[{"value":"停止销售","key":0},{"value":"恢复销售","key":1}],"jinyingfangshi":[{"value":"营利性","key":1},{"value":"非营利性","key":2}],"yunshufangshi":[{"value":"厢式货车","key":1},{"value":"其他","key":2}],"rukuleixing":[{"value":"调拨","key":1},{"value":"第三方","key":2},{"value":"空进空出","key":3},{"value":"越库","key":4},{"value":"直通入库","key":5},{"value":"正常","key":6},{"value":"订单取消","key":7},{"value":"退货入库","key":8}],"teguanyaopin":[{"value":"含麻黄碱类复方制剂","key":1},{"value":"蛋白同化制剂、肽类激素","key":2},{"value":"含特殊\r\n分的复方制剂\r\n含特殊\r\n分的复方制剂\r\n","key":3},{"value":"第二类精神药品","key":4},{"value":"疫苗","key":5},{"value":"第一类精神药品","key":6},{"value":"麻醉药品","key":8}],"yanshoupingdingyuanyin":[{"value":"空","key":0},{"value":"变质","key":1},{"value":"结晶","key":2},{"value":"错品规","key":3},{"value":"错批号","key":4},{"value":"近效期","key":5},{"value":"厂家召回","key":6},{"value":"包装模糊","key":7},{"value":"包装破损","key":8}],"youxianji":[{"value":"低","key":1},{"value":"中","key":2},{"value":"高","key":3}],"dongjie":[{"value":"冻结","key":0},{"value":"解除冻结","key":1}],"wkfs":[{"value":"空","key":0},{"value":"冷藏箱","key":1},{"value":"冷藏车","key":2}],"hexinshuxing":[{"value":"处方药","key":1},{"value":"饮片","key":2},{"value":"中药","key":3},{"value":"精神药品","key":4},{"value":"毒品","key":5},{"value":"麻醉品","key":6},{"value":"质检","key":7},{"value":"含麻黄碱","key":8},{"value":"医保","key":9},{"value":"冷藏管理","key":10},{"value":"基本药物","key":11},{"value":"电子监管","key":12},{"value":"需二次验收","key":13},{"value":"附药监报告","key":14},{"value":"进口药品","key":15}],"kuqutype":[{"value":"整件库","key":1},{"value":"零件库","key":2},{"value":"不合格品库","key":3},{"value":"退货库","key":4},{"value":"立体库","key":5},{"value":"高架库","key":6},{"value":"虚拟库","key":7},{"value":"代管库","key":8},{"value":"集货暂存区","key":9},{"value":"拣选暂存区","key":10},{"value":"收货暂存区","key":11},{"value":"待验库","key":12}],"yanghucuoshi":[{"value":"翻垛","key":1},{"value":"外观","key":2},{"value":"除湿","key":3},{"value":"加湿","key":4},{"value":"升温","key":5},{"value":"降温","key":6},{"value":"通风","key":7},{"value":"除尘","key":8}],"fapiaoleixing":[{"value":"普通发票","key":1},{"value":"增值税发票","key":2}],"bizhong":[{"value":"人民币","key":1},{"value":"美元","key":2}],"针剂":[{"value":"针剂","key":30}],"fenzutiaojain":[{"value":"按订单类型分组","key":1}],"pandianleixing":[{"value":"日常盘点","key":1},{"value":"临时盘点","key":2},{"value":"动销盘点","key":3},{"value":"全盘盘点","key":4}],"chengzairongqi":[{"value":"托盘","key":4},{"value":"周转箱","key":3},{"value":"无","key":2}],"jihuoweiyewuleixingbuyao":[{"value":"直通","key":3}],"kuquType":[{"value":"盘点库","key":13}],"nodeType":[{"value":"汇总","key":1},{"value":"明细","key":2}],"nodeStatus":[{"value":"初始","key":0},{"value":"编辑","key":10},{"value":"启用","key":20},{"value":"审核","key":30},{"value":"禁用","key":40},{"value":"删除","key":50}],"yanshoupingding":[{"value":"不合格","key":2},{"value":"合格","key":1},{"value":"待处理","key":0},{"value":"拒收","key":3}],"xiaoqidanwei":[{"value":"月","key":1},{"value":"日","key":2},{"value":"年","key":3}],"qiyong":[{"value":"是","key":1},{"value":"否","key":2}],"pandianfangshi":[{"value":"明盘","key":1},{"value":"暗盘","key":2}],"daohuofangshi":[{"value":"子公司直接发货","key":1},{"value":"客户送货","key":2},{"value":"邮局到货","key":3},{"value":"到托运公司提货","key":4},{"value":"公司到中铁提货","key":5},{"value":"托运公司送货","key":6},{"value":"公司自提","key":7},{"value":"公司到铁路提货","key":8}],"zhengjianmingcheng":[{"value":"药品生产许可证","key":1},{"value":"GMP","key":2},{"value":"第二类医疗器械经营备案凭证","key":3},{"value":"医疗器械经营许可证","key":4},{"value":"食品流通许可证","key":5},{"value":"食品经营许可证","key":6},{"value":"药品经营许可证","key":7},{"value":"GSP","key":8},{"value":"医疗器械生产企业许可证","key":9},{"value":"医疗器械生产许可证","key":10},{"value":"第一类医疗器械生产备案凭证","key":11},{"value":"食品生产许可证","key":12},{"value":"消毒产品生产企业卫生许可证","key":13},{"value":"质量保证协议","key":14},{"value":"卫生许可证","key":15},{"value":"医疗机构执业许可证","key":16}],"chengyunfangshi":[{"value":"公司运输","key":1},{"value":"客户自提","key":2},{"value":"委外运输","key":3}],"tihuofangshibuyao":[{"value":"购退","key":4}],"shangpinleibie":[{"value":"中成药","key":1},{"value":"化学药制剂","key":2},{"value":"抗生素制剂","key":3},{"value":"化学原料药","key":4},{"value":"生化药品","key":5},{"value":"处方药（禁止类除外）","key":6},{"value":"非处方药（甲类、乙类）","key":7},{"value":"保健食品","key":8},{"value":"预包装食品","key":9},{"value":"消毒用品","key":10},{"value":"日化产品","key":11},{"value":"化妆品","key":12},{"value":"日用百货","key":13},{"value":"乳制品","key":14},{"value":"I类","key":16},{"value":"II类.6801","key":50},{"value":"II类.6802","key":51},{"value":"II类.6803","key":52},{"value":"II类.6804","key":53},{"value":"II类.6805","key":54},{"value":"II类.6806","key":55},{"value":"II类.6807","key":56},{"value":"II类.6808","key":57},{"value":"II类.6809","key":58},{"value":"II类.6810","key":59},{"value":"II类.6812","key":60},{"value":"II类.6813","key":61},{"value":"II类.6815","key":62},{"value":"II类.6816","key":63},{"value":"II类.6820","key":64},{"value":"II类.6821","key":65},{"value":"II类.6822","key":66},{"value":"II类.6823","key":67},{"value":"II类.6824","key":68},{"value":"II类.6825","key":69},{"value":"II类.6826","key":70},{"value":"II类.6827","key":71},{"value":"II类.6828","key":72},{"value":"II类.6830","key":73},{"value":"II类.6831","key":74},{"value":"II类.6832","key":75},{"value":"II类.6833","key":76},{"value":"II类.6834","key":77},{"value":"II类.6840","key":78},{"value":"II类.6841","key":79},{"value":"II类.6845","key":80},{"value":"II类.6846","key":81},{"value":"II类.6854","key":82},{"value":"II类.6855","key":83},{"value":"II类.6856","key":84},{"value":"II类.6857","key":85},{"value":"II类.6858","key":86},{"value":"II类.6863","key":87},{"value":"II类.6864","key":88},{"value":"II类.6865","key":89},{"value":"II类.6866","key":90},{"value":"II类.6870","key":91},{"value":"II类.6877","key":92},{"value":"III类.6815","key":93},{"value":"III类.6821","key":94},{"value":"III类.6826","key":95},{"value":"III类.6840(不含体外诊断试剂)","key":96},{"value":"III类.6864","key":97},{"value":"III类.6866","key":98},{"value":"-","key":0}],"jihualeixing":[{"value":"已计划","key":20},{"value":"已执行","key":21},{"value":"已结束","key":22},{"value":"部分执行","key":23}],"chaibaozhuang":[{"value":"拆中包装","key":1},{"value":"拆零","key":2}],"gouduifangshi":[{"value":"按单据勾兑","key":1},{"value":"自动勾兑","key":2},{"value":"不勾兑","key":3}],"bool":[{"value":"是","key":1},{"value":"否","key":0}],"shangpincunchuxianding":[{"value":"允许跨存储区域限定","key":1},{"value":"不允许跨存储区域限定","key":0}],"chukushangpinzhuangtai":[{"value":"已计划","key":20},{"value":"已执行","key":21},{"value":"被动补货","key":22},{"value":"挂单","key":29},{"value":"冲红","key":30}],"kufangtiaojian":[{"value":"阴凉","key":1},{"value":"常温","key":2}],"huoweileixing":[{"value":"地堆","key":4},{"value":"隔板货架","key":1},{"value":"流利货架","key":2},{"value":"立体货架","key":3}],"taskType":[{"value":"零件出货","key":10},{"value":"整件出货","key":20},{"value":"主动补货","key":30},{"value":"被动补货","key":40}],"dingdanleixing":[{"value":"采购入库","key":1},{"value":"采购退出","key":2},{"value":"销售出库","key":3},{"value":"销售退回","key":4}],"cunchufenlei":[{"value":"整散分开","key":2},{"value":"整散合一","key":1}],"jianhuo":[{"value":"有","key":1},{"value":"无","key":0}],"zhiliangzhuangtai":[{"value":"合格","key":1},{"value":"不合格","key":2},{"value":"待验","key":3},{"value":"停售","key":4}],"fjhdlx1":[{"value":"空","key":1}],"yjfllx":[{"value":"正常","key":1},{"value":"已过期","key":2},{"value":"进入预警区","key":3}],"tingshou":[{"value":"停售","key":0},{"value":"解除停售","key":1}],"zhengzhaoleixing":[{"value":"营业执照","key":1},{"value":"生产/经营许可证","key":2},{"value":"医疗器械许可证","key":3},{"value":"卫生许可证","key":4},{"value":"GSP质量证书","key":5},{"value":"组织机构代码证","key":6},{"value":"药品生产许可证","key":7},{"value":"委托书","key":8}],"chacuoyuanyin":[{"value":"无差错","key":1},{"value":"错批号","key":2},{"value":"错规格","key":3},{"value":"错厂家","key":4},{"value":"错品种","key":5},{"value":"少发","key":6},{"value":"漏发","key":7},{"value":"多发","key":8}],"caiguotuichu":[{"value":"采购退出","key":0},{"value":"空进空出","key":1},{"value":"越库","key":2},{"value":"调账","key":3}],"rukushangjiazhuangtai":[{"value":"未上架","key":0},{"value":"上架完成","key":1}],"jiesuanfangshi":[{"value":"现金","key":1},{"value":"配送","key":2},{"value":"承兑","key":3},{"value":"支票","key":4},{"value":"代收","key":5},{"value":"往来","key":6},{"value":"预付","key":7},{"value":"其他","key":0}],"jianyanjieguo":[{"value":"未检","key":1},{"value":"合格","key":2},{"value":"不合格","key":3},{"value":"不确定","key":4}],"pandian":[{"value":"有","key":1},{"value":"无","key":0}],"tuikuanleixing":[{"value":"部分退款","key":1},{"value":"全部退款","key":2}],"cunquleixie":[{"value":"小客户区","key":1},{"value":"其他","key":2}],"abcselect":[{"value":"C","key":3},{"value":"B","key":2},{"value":"A","key":1}],"tihuofangshi":[{"value":"自提","key":1},{"value":"托运","key":2},{"value":"市内配送","key":3}],"neifuhezhuangtai":[{"value":"内复核未完成","key":41},{"value":"内复核完成","key":43}],"huoweileixingbuyao":[{"value":"托盘","key":4}],"chulijianyi":[{"value":"促销","key":0},{"value":"退供货商","key":1},{"value":"报损","key":2},{"value":"其他","key":3}],"chukudingdanzhuangtai":[{"value":"已计划","key":20},{"value":"已执行","key":21},{"value":"被动补货","key":22},{"value":"正在拣货","key":23},{"value":"拣货完成","key":24},{"value":"正在内复核","key":25},{"value":"内复核完成","key":26},{"value":"正在外复核","key":27},{"value":"外复核完成","key":28},{"value":"挂单","key":29},{"value":"冲红","key":30},{"value":"订单创建","key":0}],"yewuleibie":[{"value":"销售出库","key":1},{"value":"购进退出","key":2},{"value":"购进入库","key":3},{"value":"销售退回合格","key":4},{"value":"销售退回非合格","key":5},{"value":"配送返回","key":6},{"value":"库存整理","key":7},{"value":"调拨出库","key":8},{"value":"越库","key":9}],"guimo":[{"value":"大","key":1},{"value":"小","key":2}],"chucuntiaojian":[{"value":"冷藏","key":1},{"value":"常温","key":2},{"value":"阴凉","key":3}],"xiaoshouleixing":[{"value":"采购退出","key":0},{"value":"空进空出","key":1},{"value":"越库","key":2},{"value":"调账","key":3}]}
